{"key": "13a", "alive": true, "names": {"name": "Mabelie", "surname": ""}, "biological": {"sex": "f", "sexuality": "straight"}, "genetics": {"parents": "ancestors", "health": 0.6048991268798606, "birthday": ["Aprilis", 26]}, "personality": {"sins": {"superbia": [3, "happy"], "avaritia": [3, "happy"], "luxuria": [1, "not happy"], "invidia": [3, "happy"], "gula": [6, "not happy"], "ira": [4, "happy"], "acedia": [5, "happy"]}, "virtues": {"prudentia": [3, "important"], "iustitia": [5, "not important"], "temperantia": [2, "not important"], "fortitudo": [3, "not important"], "fides": [3, "not important"], "spes": [6, "important"], "caritas": [5, "important"]}}, "appearance": {"eye_color": "green", "hair_color": "brown", "hair_type": ["S", "S"]}, "social": {"2a": {"weight": 6, "index_mod": 0, "nature": "outsider"}, "5a": {"weight": 1, "index_mod": 2, "nature": "outsider"}, "6a": {"weight": 3, "index_mod": -3, "nature": "outsider"}, "9a": {"weight": 10, "index_mod": 3, "nature": "outsider"}, "10a": {"weight": 9, "index_mod": 2, "nature": "outsider"}, "12a": {"weight": 0, "index_mod": -4, "nature": "outsider"}, "4a": {"weight": 10, "index_mod": 1, "nature": "outsider"}, "7a": {"weight": 2, "index_mod": 0, "nature": "outsider"}, "8a": {"weight": 8, "index_mod": 3, "nature": "outsider"}, "14a": {"weight": 8, "index_mod": -4, "nature": "outsider"}, "15a": {"weight": 4, "index_mod": 0, "nature": "outsider"}, "18a": {"weight": -3, "index_mod": -1, "nature": "outsider"}, "24a": {"weight": 4, "index_mod": -2, "nature": "outsider"}, "28a": {"weight": 3, "index_mod": 2, "nature": "outsider"}, "29a": {"weight": -1, "index_mod": 3, "nature": "outsider"}, "31a": {"weight": -4, "index_mod": 0, "nature": "outsider"}, "32a": {"weight": -8, "index_mod": 2, "nature": "outsider"}, "37a": {"weight": 3, "index_mod": 2, "nature": "outsider"}, "40a": {"weight": 9, "index_mod": -1, "nature": "outsider"}, "41a": {"weight": 5, "index_mod": 2, "nature": "outsider"}, "42a": {"weight": 5, "index_mod": 1, "nature": "outsider"}, "46a": {"weight": 10, "index_mod": 4, "nature": "outsider"}, "48a": {"weight": -2, "index_mod": 4, "nature": "outsider"}, "49a": {"weight": 5, "index_mod": -1, "nature": "outsider"}, "50a": {"weight": -7, "index_mod": 4, "nature": "outsider"}, "51a": {"weight": 4, "index_mod": -3, "nature": "outsider"}, "57a": {"weight": 8, "index_mod": 3, "nature": "outsider"}, "59a": {"weight": 3, "index_mod": 0, "nature": "outsider"}, "66a": {"weight": -2, "index_mod": -1, "nature": "outsider"}, "68a": {"weight": -1, "index_mod": 5, "nature": "outsider"}, "69a": {"weight": -4, "index_mod": 2, "nature": "outsider"}, "70a": {"weight": 5, "index_mod": 0, "nature": "outsider"}, "17a": {"weight": 8, "index_mod": 6, "nature": "outsider"}, "25a": {"weight": -9, "index_mod": 1, "nature": "outsider"}, "34a": {"weight": -6, "index_mod": 2, "nature": "outsider"}, "38a": {"weight": -7, "index_mod": -1, "nature": "outsider"}, "43a": {"weight": 2, "index_mod": 0, "nature": "outsider"}, "44a": {"weight": 6, "index_mod": 6, "nature": "outsider"}, "45a": {"weight": 3, "index_mod": 2, "nature": "outsider"}, "54a": {"weight": -2, "index_mod": -2, "nature": "outsider"}, "61a": {"weight": 0, "index_mod": 1, "nature": "outsider"}, "64a": {"weight": -3, "index_mod": 6, "nature": "outsider"}, "13c1": {"weight": 13, "index_mod": 2, "nature": "parent"}, "13c2": {"weight": 17, "index_mod": 3, "nature": "parent"}, "13c3": {"weight": 22, "index_mod": 0, "nature": "parent"}, "13c4": {"weight": 39, "index_mod": 1, "nature": "parent"}, "13c5": {"weight": 36, "index_mod": -1, "nature": "parent"}, "13c6": {"weight": 10, "index_mod": 3, "nature": "parent"}, "13c7": {"weight": 18, "index_mod": 4, "nature": "parent"}, "13c8": {"weight": 37, "index_mod": 3, "nature": "parent"}, "13c9": {"weight": 21, "index_mod": 0, "nature": "parent"}}, "procedural": {"age": 26, "married": true, "no_children": 10, "relationships": ["13"], "events": ["Got married at 12 to Alebaren.", "Lost their child Heylewigis when Heylewigis was 3 years old."]}}