{"key": "1498c2", "alive": true, "names": {"name": "Ermegardis", "surname": "van Mourin"}, "biological": {"sex": "f", "sexuality": "straight"}, "genetics": {"parents": "Egbertus and Ghela", "health": 0.7708504518129708}, "personality": {"sins": {"superbia": 1, "avaritia": 0, "luxuria": 0, "invidia": 2, "gula": 3, "ira": 2, "acedia": 1}, "virtues": {"prudentia": 5, "iustitia": 1, "temperantia": 5, "fortitudo": 2, "fides": 2, "spes": 5, "caritas": 4}}, "appearance": "dark golden brown", "procedural": {"age": 16, "married": false, "events": {}}}