{"alive": true, "house": "Cingel.B.2", "names": {"name": "Leanne", "nickname": "", "surname": ""}, "biological": {"parents": "159", "sex": "f", "sexuality": "straight", "health": 0.7520855195825942, "birthday": ["Septembris", 7, 1371]}, "appearance": {"hair_color": "strawberry blonde", "hair_type": ["S", "S"], "eye_color": "green"}, "parents": ["159b and 159a", "Abelkijn and Ymmekine"], "procedural": {"age": 29, "married": true, "no_children": 2, "connections": {"family": {}, "outsider": {}, "sibling": {"159c5": {"weight": 9, "index_mod": 7, "nature": "sibling"}, "159c6": {"weight": 10, "index_mod": 8, "nature": "sibling"}}, "parent": {"794c1": {"weight": 14, "index_mod": -1, "nature": "parent"}, "794c2": {"weight": 10, "index_mod": 9, "nature": "parent"}}}}, "personality": {"sins": {"superbia": [3, "happy"], "avaritia": [3, "happy"], "luxuria": [2, "not happy"], "invidia": [6, "happy"], "gula": [5, "happy"], "ira": [4, "happy"], "acedia": [3, "happy"]}, "virtues": {"prudentia": [5, "important"], "iustitia": [2, "not important"], "temperantia": [3, "not important"], "fortitudo": [6, "not important"], "fides": [3, "not important"], "spes": [5, "important"], "caritas": [3, "important"]}}, "events": {"1371": ["Leanne was born in Cingel in 1371."], "1376": ["Lost sibling bertrade in 1376 when bertrade was 3.", "Lost sibling Thitardo in 1376 when Thitardo was 2."], "1384": ["Lost sibling Jacobus in 1384 when Jacobus was 2."], "1388": ["Lost father at the age of 17.", "Lost father at the age of 17."], "1392": ["Lost mother at the age of 21.", "Became caretaker of Thedwi at age 22.", "Became breadwinner of household."], "1393": ["Lost sibling Godeweris in 1393 when Godeweris was 17."], "1395": ["Got married to Hille at age 25 in 1395.", "Had Hille move in at Cingel.B.2 after marriage."], "1398": ["Gave birth to Valken in 1398 at age 27."], "1399": ["Gave birth to Ricout in 1399 at age 28."]}}