{"alive": true, "house": "Uterechse straet.A.1", "names": {"name": "Segherarden", "nickname": "", "surname": ""}, "biological": {"parents": "1", "sex": "f", "sexuality": "straight", "health": 0.5728147048801343, "birthday": ["Martius", 2, 1383]}, "appearance": {"hair_color": "brown", "hair_type": ["C", "S"], "eye_color": "blue"}, "parents": ["1b and 1a", "Rembrandus and Siwa"], "procedural": {"age": 17, "married": false, "no_children": 0, "connections": {"family": {}, "outsider": {}, "sibling": {"1c1": {"weight": 5, "index_mod": 15, "nature": "sibling"}, "1c2": {"weight": 16, "index_mod": 15, "nature": "sibling"}, "1c3": {"weight": 21, "index_mod": 15, "nature": "sibling"}, "1c4": {"weight": 25, "index_mod": 15, "nature": "sibling"}, "1c5": {"weight": 18, "index_mod": 15, "nature": "sibling"}, "1c6": {"weight": 9, "index_mod": 15, "nature": "sibling"}, "1c7": {"weight": 22, "index_mod": 15, "nature": "sibling"}, "1c10": {"weight": 5, "index_mod": 11, "nature": "sibling"}}, "parent": {}}}, "personality": {"sins": {"superbia": [4, "happy"], "avaritia": [6, "not happy"], "luxuria": [2, "not happy"], "invidia": [3, "happy"], "gula": [4, "happy"], "ira": [5, "happy"], "acedia": [3, "happy"]}, "virtues": {"prudentia": [3, "important"], "iustitia": [4, "important"], "temperantia": [7, "not important"], "fortitudo": [6, "important"], "fides": [6, "important"], "spes": [6, "important"], "caritas": [5, "not important"]}}, "events": ["Segherarden was born in Uterechse straet in 1383.", "Lost mother at the age of 1 in childbirth.", "Lost sibling bertrade when bertrade was 16 in 1397."]}