{"alive": false, "house": "Die Camp.B.13", "names": {"name": "Gheesen", "nickname": "Smout", "surname": ""}, "biological": {"parents": "201", "sex": "f", "sexuality": "straight", "health": 0.847667443283848, "birthday": ["Februarius", 5, 1372]}, "appearance": {"hair_color": "red", "hair_type": ["S", "S"], "eye_color": "blue"}, "parents": ["201b and 201a", "Thieleman and Ghoudekinen"], "procedural": {"age": 5, "married": false, "no_children": 0, "connections": {"family": {}, "outsider": {}, "sibling": {}, "parent": {}}}, "personality": {"sins": {"superbia": [5, "happy"], "avaritia": [5, "happy"], "luxuria": [2, "not happy"], "invidia": [5, "happy"], "gula": [2, "happy"], "ira": [2, "happy"], "acedia": [3, "happy"]}, "virtues": {"prudentia": [5, "important"], "iustitia": [4, "important"], "temperantia": [6, "important"], "fortitudo": [2, "not important"], "fides": [3, "important"], "spes": [4, "important"], "caritas": [4, "important"]}}, "events": {"1372": ["Gheesen was born in Die Camp in 1372."], "1376": ["Died at age 5."]}}