{"key": "2935c4", "alive": true, "names": {"name": "Snellekine", "surname": "Scamel"}, "biological": {"sex": "m", "sexuality": "straight"}, "genetics": {"parents": "Evergero and Ghela", "health": 0.7874924908054732}, "personality": {"sins": {"superbia": 2, "avaritia": 2, "luxuria": 3, "invidia": 2, "gula": 5, "ira": 5, "acedia": 3}, "virtues": {"prudentia": 5, "iustitia": 1, "temperantia": 2, "fortitudo": 1, "fides": 4, "spes": 0, "caritas": 0}}, "appearance": "cool brown", "procedural": {"age": 5, "married": false, "events": {}}}