{"alive": false, "house": "Koe straet.B.0", "names": {"name": "Hilduardis", "nickname": "", "surname": ""}, "biological": {"parents": "ancestors", "sex": "f", "sexuality": "straight", "health": 0.2668735951205289, "birthday": ["Septembris", 6, 1346]}, "appearance": {"hair_color": "brown", "hair_type": ["S", "C"], "eye_color": "blue"}, "parents": ["ancestors", "ancestors"], "procedural": {"age": 46, "married": false, "no_children": 7, "connections": {"family": {}, "outsider": {}, "sibling": {}, "parent": {}}}, "personality": {"sins": {"superbia": [4, "happy"], "avaritia": [3, "happy"], "luxuria": [5, "happy"], "invidia": [2, "happy"], "gula": [2, "happy"], "ira": [4, "happy"], "acedia": [3, "happy"]}, "virtues": {"prudentia": [3, "important"], "iustitia": [6, "important"], "temperantia": [5, "not important"], "fortitudo": [6, "important"], "fides": [4, "important"], "spes": [5, "not important"], "caritas": [4, "important"]}}, "events": {"1370": ["Hilduardis moved to Koe straet.B.0 after marriage.", "Got married to Reuro at age 24 in 1370."], "1371": ["Gave birth to Mourin in 1371 at age 25."], "1374": ["Gave birth to Oda in 1374 at age 28."], "1375": ["Gave birth to Natelien in 1375 at age 29."], "1379": ["Lost daughter Lisebette when Lisebette was 0 years old.", "Gave birth to stillborn Lisebette in 1379 at age 33."], "1384": ["Gave birth to Oda in 1384 at age 38."], "1385": ["Gave birth to Amelgeir in 1385 at age 39."], "1387": ["Gave birth to Oda in 1387 at age 41.", "Became a widow at 47."], "1391": ["Died at age 46."]}}