{"key": "366c14", "alive": true, "names": {"name": "Hille", "surname": null}, "biological": {"sex": "f", "sexuality": "straight"}, "genetics": {"parents": "Wilbord and Folqui", "health": 0.9454067760477206}, "personality": {"sins": {"superbia": 4, "avaritia": 2, "luxuria": 0, "invidia": 4, "gula": 1, "ira": 0, "acedia": 4}, "virtues": {"prudentia": 1, "iustitia": 5, "temperantia": 3, "fortitudo": 0, "fides": 4, "spes": 5, "caritas": 3}}, "appearance": "dark champagne", "procedural": {"age": 2, "married": false, "events": {}}}