{"key": "4720c1", "alive": true, "names": {"name": "Ricmoden", "surname": null}, "biological": {"sex": "f", "sexuality": "straight"}, "genetics": {"parents": "Bodekine and Sophia", "health": 0.9448468294598513}, "personality": {"sins": {"superbia": 5, "avaritia": 2, "luxuria": 5, "invidia": 5, "gula": 2, "ira": 3, "acedia": 5}, "virtues": {"prudentia": 0, "iustitia": 5, "temperantia": 2, "fortitudo": 3, "fides": 0, "spes": 2, "caritas": 0}}, "appearance": "espresso", "procedural": {"age": 5, "married": false, "events": {}}}