{"alive": true, "house": "Op Havick1.A.12", "names": {"name": "Salomon", "nickname": "", "surname": "Menseszoon"}, "biological": {"parents": "517", "sex": "m", "sexuality": "straight", "health": 0.7325723149238214, "birthday": ["Aprilis", 7, 1399]}, "appearance": {"hair_color": "brown", "hair_type": ["S", "S"], "eye_color": "blue"}, "parents": ["517b and 517a", "Mense and Agnes"], "procedural": {"age": 1, "married": false, "no_children": 0, "connections": {"family": {}, "outsider": {}, "sibling": {"517c1": {"weight": 20, "index_mod": 12, "nature": "sibling"}, "517c2": {"weight": 5, "index_mod": 12, "nature": "sibling"}, "517c4": {"weight": 7, "index_mod": 12, "nature": "sibling"}, "517c5": {"weight": 7, "index_mod": 12, "nature": "sibling"}}, "parent": {"517a": {"weight": 46, "index_mod": 12, "nature": "parent"}, "517b": {"weight": 12, "index_mod": 12, "nature": "parent"}}}, "events": ["Salomon moved to Op Havick1.A.12 because of birthed."]}, "personality": {"sins": {"superbia": [6, "not happy"], "avaritia": [4, "happy"], "luxuria": [6, "not happy"], "invidia": [5, "happy"], "gula": [1, "happy"], "ira": [5, "happy"], "acedia": [2, "not happy"]}, "virtues": {"prudentia": [1, "important"], "iustitia": [2, "not important"], "temperantia": [6, "important"], "fortitudo": [3, "not important"], "fides": [3, "not important"], "spes": [4, "not important"], "caritas": [6, "important"]}}}