{"key": "552c8", "alive": false, "names": {"name": "Fellen", "surname": null}, "biological": {"sex": "m", "sexuality": "straight"}, "genetics": {"parents": "Eligius and Ermegardis", "health": 0.6509993698143638}, "personality": {"sins": {"superbia": 2, "avaritia": 1, "luxuria": 2, "invidia": 0, "gula": 5, "ira": 5, "acedia": 0}, "virtues": {"prudentia": 4, "iustitia": 0, "temperantia": 2, "fortitudo": 2, "fides": 3, "spes": 0, "caritas": 1}}, "appearance": "espresso", "procedural": {"age": 1, "married": false, "events": {}}}