{"alive": false, "house": "Marcktgang.C.1", "names": {"name": "Butsel", "nickname": "", "surname": ""}, "biological": {"parents": "ancestors", "sex": "m", "sexuality": "straight", "health": 0.6622158771698017, "birthday": ["Ianuarius", 4, 1337]}, "appearance": {"hair_color": "brown", "hair_type": ["S", "S"], "eye_color": "brown"}, "parents": ["ancestors", "ancestors"], "procedural": {"age": 52, "married": false, "relationships": ["554b, 554a"], "no_children": 1, "children": null}, "personality": {"sins": {"superbia": [2, "happy"], "avaritia": [4, "happy"], "luxuria": [2, "not happy"], "invidia": [5, "happy"], "gula": [4, "happy"], "ira": [5, "happy"], "acedia": [6, "not happy"]}, "virtues": {"prudentia": [4, "important"], "iustitia": [4, "not important"], "temperantia": [2, "not important"], "fortitudo": [5, "important"], "fides": [3, "not important"], "spes": [5, "important"], "caritas": [5, "important"]}}, "network": {"family": {}, "outsider": {}, "sibling": {}, "parent": {"554c1": {"weight": 4.0, "index_mod": 5, "nature": "parent"}}, "other": {"554a": {"weight": 23, "index_mod": 7, "nature": "other"}}}, "events": {"1370": ["Butsel moved to Marcktgang.C.1 after marriage.", "Got married to Godeweris at age 33 in 1370.", "Became breadwinner of household."], "1375": ["Became a widower at 38.", "Lost his wife Godeweris while she was giving birth to Godeweris in 1375.", "Became caretaker of Godeweris at age 39."], "1377": ["Lost daughter Godeweris when Godeweris was 3 years old."], "1388": ["Died at age 52."]}}