{"key": "5707c1", "alive": true, "names": {"name": "Itsburgis", "surname": null}, "biological": {"sex": "f", "sexuality": "straight"}, "genetics": {"parents": "Daniel and Berta", "health": 0.8433657539582358}, "personality": {"sins": {"superbia": 1, "avaritia": 0, "luxuria": 0, "invidia": 1, "gula": 3, "ira": 3, "acedia": 1}, "virtues": {"prudentia": 4, "iustitia": 5, "temperantia": 4, "fortitudo": 1, "fides": 2, "spes": 4, "caritas": 0}}, "appearance": "ginger", "procedural": {"age": 3, "married": false, "events": {}}}