{"alive": false, "house": "Mooierstraet.B.3", "names": {"name": "Breghtgherus", "nickname": "Crudepenninx", "surname": "Rippertiszoon"}, "biological": {"parents": "648", "sex": "m", "sexuality": "straight", "health": 0.44810076789448483, "birthday": ["Maius", 8, 1395]}, "appearance": {"hair_color": "blonde", "hair_type": ["C", "S"], "eye_color": "brown"}, "parents": ["144c1 and 64c2", "Ripperti and Aleberna"], "procedural": {"age": 0, "married": false, "relationships": [], "no_children": 0, "children": null}, "personality": {"sins": {"superbia": [6, "not happy"], "avaritia": [6, "happy"], "luxuria": [5, "happy"], "invidia": [5, "happy"], "gula": [5, "happy"], "ira": [6, "not happy"], "acedia": [5, "happy"]}, "virtues": {"prudentia": [3, "not important"], "iustitia": [5, "not important"], "temperantia": [3, "not important"], "fortitudo": [1, "important"], "fides": [1, "not important"], "spes": [2, "not important"], "caritas": [2, "important"]}}, "network": {"household": {"144c1": {"weight": 70, "index_mod": 21, "nature": "household", "length": 1}, "64c2": {"weight": 55, "index_mod": 21, "nature": "household", "length": 1}, "648c1": {"weight": 69.0, "index_mod": 21, "nature": "household", "length": 1}, "648c2": {"weight": 109.5, "index_mod": 21, "nature": "household", "length": 1}}, "section": {"252c1": {"weight": 41, "index_mod": 21, "nature": "section", "length": 2}, "636c1": {"weight": 85.0, "index_mod": 21, "nature": "section", "length": 2}}, "street": {"453c2": {"weight": 40, "index_mod": 21, "nature": "street", "length": 3}, "453c4": {"weight": 41, "index_mod": 21, "nature": "street", "length": 3}, "453c5": {"weight": 16, "index_mod": 21, "nature": "street", "length": 3}, "453c6": {"weight": 65, "index_mod": 21, "nature": "street", "length": 3}, "454c1": {"weight": 37, "index_mod": 21, "nature": "street", "length": 3}, "454c2": {"weight": 53, "index_mod": 21, "nature": "street", "length": 3}, "454c5": {"weight": 27, "index_mod": 21, "nature": "street", "length": 3}, "454c6": {"weight": 40, "index_mod": 21, "nature": "street", "length": 3}, "454c7": {"weight": 46.0, "index_mod": 21, "nature": "street", "length": 3}, "532c1": {"weight": 61, "index_mod": 21, "nature": "street", "length": 3}, "616c1": {"weight": 74.5, "index_mod": 21, "nature": "street", "length": 3}, "616c3": {"weight": 29.5, "index_mod": 21, "nature": "street", "length": 3}, "616c4": {"weight": 67.0, "index_mod": 21, "nature": "street", "length": 3}}, "neighborhood": {}, "city": {}, "outside": {}}, "events": {"1395": ["Breghtgherus was born in Mooierstraet in 1395.", "Died at age 0 days after being born."]}}