{"alive": false, "house": "Die Camp.A.4", "names": {"name": "Goneir", "nickname": "", "surname": ""}, "biological": {"parents": "ancestors", "sex": "f", "sexuality": "straight", "health": 0.7121460374818933, "birthday": ["Octobris", 9, 1336]}, "appearance": {"hair_color": "strawberry blonde", "hair_type": ["S", "S"], "eye_color": "blue"}, "parents": ["ancestors", "ancestors"], "procedural": {"age": 49, "married": false, "no_children": 0, "connections": {"family": {}, "outsider": {}, "sibling": {}, "parent": {}}}, "personality": {"sins": {"superbia": [3, "happy"], "avaritia": [4, "happy"], "luxuria": [5, "happy"], "invidia": [7, "happy"], "gula": [4, "happy"], "ira": [3, "happy"], "acedia": [1, "not happy"]}, "virtues": {"prudentia": [3, "important"], "iustitia": [6, "important"], "temperantia": [3, "important"], "fortitudo": [7, "important"], "fides": [3, "not important"], "spes": [5, "important"], "caritas": [3, "important"]}}, "events": {"1370": ["Goneir moved to Die Camp.A.4 after marriage.", "Goneir moved to Die Camp.A.4 in 1370."], "1377": ["Became breadwinner of household."], "1384": ["Died at age 49."]}}