{"key": "8452c1", "alive": true, "names": {"name": "Michiel", "surname": null}, "biological": {"sex": "m", "sexuality": "straight"}, "genetics": {"parents": "Godino and Myrthel", "health": 0.6500098770588695}, "personality": {"sins": {"superbia": 1, "avaritia": 1, "luxuria": 4, "invidia": 3, "gula": 4, "ira": 2, "acedia": 2}, "virtues": {"prudentia": 2, "iustitia": 0, "temperantia": 5, "fortitudo": 2, "fides": 0, "spes": 5, "caritas": 3}}, "appearance": "light blonde", "procedural": {"age": 1, "married": false, "events": {}}}