{"key": "911c3", "alive": false, "names": {"name": "Andreas", "surname": null}, "biological": {"sex": "m", "sexuality": "gay"}, "genetics": {"parents": "Ivone and Ermegardis", "health": 0.9523946278730543}, "personality": {"sins": {"superbia": 3, "avaritia": 0, "luxuria": 5, "invidia": 1, "gula": 3, "ira": 1, "acedia": 4}, "virtues": {"prudentia": 2, "iustitia": 5, "temperantia": 2, "fortitudo": 4, "fides": 2, "spes": 1, "caritas": 2}}, "appearance": "chocolate brown", "procedural": {"age": 1, "married": false, "events": {}}}